yetanotherschema/__init__.py
yetanotherschema/api.py
yetanotherschema/exceptions.py
yetanotherschema/core/__init__.py
yetanotherschema/core/context_store.py
yetanotherschema/core/db_manager.py
yetanotherschema/core/query_engine.py
yetanotherschema/core/value_store.py
yetanotherschema-0.1.1.dist-info/licenses/LICENSE
yetanotherschema-0.1.1.dist-info/METADATA
yetanotherschema-0.1.1.dist-info/WHEEL
yetanotherschema-0.1.1.dist-info/top_level.txt
yetanotherschema-0.1.1.dist-info/RECORD
