Metadata-Version: 2.4
Name: yetanotherschema
Version: 0.1.1
Summary: A semantic database for auditable data with append-only corrections and full traceability
Author: Krishnamoorthy Sankaran
License: MIT
Project-URL: Homepage, https://github.com/yourusername/yetanotherschema
Project-URL: Documentation, https://github.com/yourusername/yetanotherschema/blob/main/README.md
Project-URL: Repository, https://github.com/yourusername/yetanotherschema
Project-URL: Issues, https://github.com/yourusername/yetanotherschema/issues
Keywords: database,semantic,audit,temporal,duckdb,polars
Classifier: Development Status :: 3 - Alpha
Classifier: Intended Audience :: Developers
Classifier: License :: OSI Approved :: MIT License
Classifier: Programming Language :: Python :: 3
Classifier: Programming Language :: Python :: 3.8
Classifier: Programming Language :: Python :: 3.9
Classifier: Programming Language :: Python :: 3.10
Classifier: Programming Language :: Python :: 3.11
Classifier: Programming Language :: Python :: 3.12
Classifier: Programming Language :: Python :: 3.13
Classifier: Topic :: Database
Classifier: Topic :: Software Development :: Libraries :: Python Modules
Requires-Python: >=3.8
License-File: LICENSE
Requires-Dist: duckdb>=1.0.0
Requires-Dist: polars>=0.20.0
Requires-Dist: pyarrow>=10.0.0
Requires-Dist: toml>=0.10.0
Requires-Dist: python-dateutil>=2.8.0
Dynamic: license-file
